PollingRequest/__init__.py
pollingrequest-1.0.0.dist-info/LICENSE
pollingrequest-1.0.0.dist-info/METADATA
pollingrequest-1.0.0.dist-info/WHEEL
pollingrequest-1.0.0.dist-info/RECORD
